pyiceberg_firestore_gcs/__init__.py
pyiceberg_firestore_gcs/compaction.py
pyiceberg_firestore_gcs/firestore_catalog.py
pyiceberg_firestore_gcs/parquet_manifest.py
pyiceberg_firestore_gcs/to_int.py
pyiceberg_firestore_gcs/view.py
pyiceberg_firestore_gcs/fileio/gcs_fileio.py
pyiceberg_firestore_gcs/migrate/export_to_iceberg.py
pyiceberg_firestore_gcs/migrate/import_from_iceberg.py
pyiceberg_firestore_gcs-0.3.0.dist-info/licenses/LICENSE
scripts/create_benchmark_tables.py
scripts/create_clickbench_views.py
scripts/create_opteryx_tables.py
scripts/explore_opteryx_data.py
scripts/explore_opteryx_detail.py
scripts/fix_tweets_table.py
scripts/rewrite_opteryx_tables.py
tests/conftest.py
tests/create_real_test_data.py
tests/create_table.py
tests/create_test_metadata.py
tests/debug_date_stats.py
tests/read_table.py
tests/regenerate_manifest.py
tests/test_brin_pruning.py
tests/test_compaction.py
tests/test_compatibility_flag.py
tests/test_date_pruning.py
tests/test_debug_write.py
tests/test_encoding.py
tests/test_endian_debug.py
tests/test_filter_pruning.py
tests/test_manifest_write_read.py
tests/test_parquet_manifest.py
tests/test_parquet_read.py
tests/test_pruning_edge_cases.py
tests/test_pruning_unit.py
tests/test_pyarrow_storage.py
tests/test_view_metadata.py
tests/verify_parquet_manifest.py
tests/verify_pruning.py
tools/run_opteryx_with_avro_trace.py
tools/trace_avro_and_run.py
pyiceberg_firestore_gcs-0.3.0.dist-info/METADATA
pyiceberg_firestore_gcs-0.3.0.dist-info/WHEEL
pyiceberg_firestore_gcs-0.3.0.dist-info/top_level.txt
pyiceberg_firestore_gcs-0.3.0.dist-info/RECORD
