Metadata-Version: 2.4
Name: pyiceberg_firestore_gcs
Version: 0.3.0
Summary: Opteryx Cloud Iceberg Catalog
Requires-Python: >=3.9
License-File: LICENSE
Requires-Dist: google-cloud-firestore==2.22.0
Requires-Dist: google-cloud-storage==3.7.0
Requires-Dist: orso==0.0.226
Requires-Dist: pyarrow==22.0.0
Requires-Dist: pyiceberg==0.10.0
Requires-Dist: requests==2.32.5
Dynamic: license-file
